{
  "_links": {
    "self": {
      "href": "https://eu.api.blizzard.com/data/wow/item/139431?namespace=static-11.1.0_59095-eu"
    }
  },
  "icon_path": "data\\icons\\inv_crate_02.jpg",
  "id": 139431,
  "inventory_type": {
    "name": "Non-equippable",
    "type": "NON_EQUIP"
  },
  "is_equippable": false,
  "is_stackable": false,
  "item_class": {
    "id": 0,
    "key": {
      "href": "https://eu.api.blizzard.com/data/wow/item-class/0?namespace=static-11.1.0_59095-eu"
    },
    "name": "Consumable"
  },
  "item_subclass": {
    "id": 8,
    "key": {
      "href": "https://eu.api.blizzard.com/data/wow/item-class/0/item-subclass/8?namespace=static-11.1.0_59095-eu"
    },
    "name": "Other"
  },
  "level": 1,
  "max_count": 0,
  "media": {
    "id": 139431,
    "key": {
      "href": "https://eu.api.blizzard.com/data/wow/media/item/139431?namespace=static-11.1.0_59095-eu"
    }
  },
  "name": "Crate of Ratstallion Harnesses",
  "preview_item": {
    "inventory_type": {
      "name": "Non-equippable",
      "type": "NON_EQUIP"
    },
    "is_subclass_hidden": true,
    "item": {
      "id": 139431,
      "key": {
        "href": "https://eu.api.blizzard.com/data/wow/item/139431?namespace=static-11.1.0_59095-eu"
      }
    },
    "item_class": {
      "id": 0,
      "key": {
        "href": "https://eu.api.blizzard.com/data/wow/item-class/0?namespace=static-11.1.0_59095-eu"
      },
      "name": "Consumable"
    },
    "item_subclass": {
      "id": 8,
      "key": {
        "href": "https://eu.api.blizzard.com/data/wow/item-class/0/item-subclass/8?namespace=static-11.1.0_59095-eu"
      },
      "name": "Other"
    },
    "media": {
      "id": 139431,
      "key": {
        "href": "https://eu.api.blizzard.com/data/wow/media/item/139431?namespace=static-11.1.0_59095-eu"
      }
    },
    "name": "Crate of Ratstallion Harnesses",
    "quality": {
      "name": "Common",
      "type": "COMMON"
    },
    "sell_price": {
      "display_strings": {
        "copper": "1",
        "gold": "0",
        "header": "Sell Price:",
        "silver": "0"
      },
      "value": 1
    },
    "spells": [
      {
        "description": "Use: Place a crate of Ratstallion Harnesses that you and other players can use to mount while in the Underbelly.\r\n\r\nContains 25 mounts.",
        "spell": {
          "id": 220229,
          "key": {
            "href": "https://eu.api.blizzard.com/data/wow/spell/220229?namespace=static-11.1.0_59095-eu"
          },
          "name": "Ratstallion Harnesses"
        }
      }
    ]
  },
  "purchase_price": 4,
  "purchase_quantity": 1,
  "quality": {
    "name": "Common",
    "type": "COMMON"
  },
  "required_level": 1,
  "sell_price": 1
}