{
  "_links": {
    "self": {
      "href": "https://eu.api.blizzard.com/data/wow/item/15971?namespace=static-11.1.0_59095-eu"
    }
  },
  "id": 15971,
  "name": "Aboriginal Rod",
  "quality": {
    "type": "UNCOMMON",
    "name": "Uncommon"
  },
  "level": 12,
  "required_level": 7,
  "media": {
    "key": {
      "href": "https://eu.api.blizzard.com/data/wow/media/item/15971?namespace=static-11.1.0_59095-eu"
    },
    "id": 15971
  },
  "item_class": {
    "key": {
      "href": "https://eu.api.blizzard.com/data/wow/item-class/4?namespace=static-11.1.0_59095-eu"
    },
    "name": "Armor",
    "id": 4
  },
  "item_subclass": {
    "key": {
      "href": "https://eu.api.blizzard.com/data/wow/item-class/4/item-subclass/0?namespace=static-11.1.0_59095-eu"
    },
    "name": "Miscellaneous",
    "id": 0
  },
  "inventory_type": {
    "type": "HOLDABLE",
    "name": "Held In Off-hand"
  },
  "purchase_price": 4673,
  "sell_price": 934,
  "max_count": 0,
  "is_equippable": true,
  "is_stackable": false,
  "preview_item": {
    "item": {
      "key": {
        "href": "https://eu.api.blizzard.com/data/wow/item/15971?namespace=static-11.1.0_59095-eu"
      },
      "id": 15971
    },
    "context": 0,
    "bonus_list": [
      6655
    ],
    "quality": {
      "type": "UNCOMMON",
      "name": "Uncommon"
    },
    "name": "Aboriginal Rod",
    "media": {
      "key": {
        "href": "https://eu.api.blizzard.com/data/wow/media/item/15971?namespace=static-11.1.0_59095-eu"
      },
      "id": 15971
    },
    "item_class": {
      "key": {
        "href": "https://eu.api.blizzard.com/data/wow/item-class/4?namespace=static-11.1.0_59095-eu"
      },
      "name": "Armor",
      "id": 4
    },
    "item_subclass": {
      "key": {
        "href": "https://eu.api.blizzard.com/data/wow/item-class/4/item-subclass/0?namespace=static-11.1.0_59095-eu"
      },
      "name": "Miscellaneous",
      "id": 0
    },
    "inventory_type": {
      "type": "HOLDABLE",
      "name": "Held In Off-hand"
    },
    "binding": {
      "type": "ON_EQUIP",
      "name": "Binds when equipped"
    },
    "stats": [
      {
        "type": {
          "type": "INTELLECT",
          "name": "Intellect"
        },
        "value": 421,
        "display": {
          "display_string": "+421 Intellect",
          "color": {
            "r": 255,
            "g": 255,
            "b": 255,
            "a": 1.0
          }
        }
      },
      {
        "type": {
          "type": "STAMINA",
          "name": "Stamina"
        },
        "value": 248,
        "display": {
          "display_string": "+248 Stamina",
          "color": {
            "r": 255,
            "g": 255,
            "b": 255,
            "a": 1.0
          }
        }
      }
    ],
    "sell_price": {
      "value": 276681,
      "display_strings": {
        "header": "Sell Price:",
        "gold": "27",
        "silver": "66",
        "copper": "81"
      }
    },
    "requirements": {
      "level": {
        "value": 7,
        "display_string": "Requires Level 7"
      }
    },
    "level": {
      "value": 357,
      "display_string": "Item Level 357"
    },
    "is_subclass_hidden": true
  },
  "purchase_quantity": 1,
  "appearances": [
    {
      "key": {
        "href": "https://eu.api.blizzard.com/data/wow/item-appearance/3837?namespace=static-11.1.0_59095-eu"
      },
      "id": 3837
    }
  ]
}