{
  "_links": {
    "self": {
      "href": "https://eu.api.blizzard.com/data/wow/item/188034?namespace=static-11.1.0_59095-eu"
    }
  },
  "appearances": [
    {
      "id": 57155,
      "key": {
        "href": "https://eu.api.blizzard.com/data/wow/item-appearance/57155?namespace=static-11.1.0_59095-eu"
      }
    },
    {
      "id": 57173,
      "key": {
        "href": "https://eu.api.blizzard.com/data/wow/item-appearance/57173?namespace=static-11.1.0_59095-eu"
      }
    }
  ],
  "icon_path": "data\\icons\\inv_plate_broker_c_01_bracer.jpg",
  "id": 188034,
  "inventory_type": {
    "name": "Wrist",
    "type": "WRIST"
  },
  "is_equippable": true,
  "is_stackable": false,
  "item_class": {
    "id": 4,
    "key": {
      "href": "https://eu.api.blizzard.com/data/wow/item-class/4?namespace=static-11.1.0_59095-eu"
    },
    "name": "Armor"
  },
  "item_subclass": {
    "id": 4,
    "key": {
      "href": "https://eu.api.blizzard.com/data/wow/item-class/4/item-subclass/4?namespace=static-11.1.0_59095-eu"
    },
    "name": "Plate"
  },
  "level": 226,
  "max_count": 0,
  "media": {
    "id": 188034,
    "key": {
      "href": "https://eu.api.blizzard.com/data/wow/media/item/188034?namespace=static-11.1.0_59095-eu"
    }
  },
  "name": "Harmonium Vambrace",
  "preview_item": {
    "armor": {
      "display": {
        "color": {
          "a": 1.0,
          "b": 255,
          "g": 255,
          "r": 255
        },
        "display_string": "72 Armor"
      },
      "value": 72
    },
    "binding": {
      "name": "Binds when equipped",
      "type": "ON_EQUIP"
    },
    "durability": {
      "display_string": "Durability 40 / 40",
      "value": 40
    },
    "inventory_type": {
      "name": "Wrist",
      "type": "WRIST"
    },
    "item": {
      "id": 188034,
      "key": {
        "href": "https://eu.api.blizzard.com/data/wow/item/188034?namespace=static-11.1.0_59095-eu"
      }
    },
    "item_class": {
      "id": 4,
      "key": {
        "href": "https://eu.api.blizzard.com/data/wow/item-class/4?namespace=static-11.1.0_59095-eu"
      },
      "name": "Armor"
    },
    "item_subclass": {
      "id": 4,
      "key": {
        "href": "https://eu.api.blizzard.com/data/wow/item-class/4/item-subclass/4?namespace=static-11.1.0_59095-eu"
      },
      "name": "Plate"
    },
    "level": {
      "display_string": "Item Level 226",
      "value": 226
    },
    "media": {
      "id": 188034,
      "key": {
        "href": "https://eu.api.blizzard.com/data/wow/media/item/188034?namespace=static-11.1.0_59095-eu"
      }
    },
    "name": "Harmonium Vambrace",
    "quality": {
      "name": "Uncommon",
      "type": "UNCOMMON"
    },
    "requirements": {
      "level": {
        "display_string": "Requires Level 60",
        "value": 60
      }
    },
    "sell_price": {
      "display_strings": {
        "copper": "78",
        "gold": "3",
        "header": "Sell Price:",
        "silver": "7"
      },
      "value": 30778
    },
    "stats": [
      {
        "display": {
          "color": {
            "a": 1.0,
            "b": 255,
            "g": 255,
            "r": 255
          },
          "display_string": "+25 Intellect"
        },
        "type": {
          "name": "Intellect",
          "type": "INTELLECT"
        },
        "value": 25
      },
      {
        "display": {
          "color": {
            "a": 1.0,
            "b": 128,
            "g": 128,
            "r": 128
          },
          "display_string": "+25 Strength"
        },
        "is_negated": true,
        "type": {
          "name": "Strength",
          "type": "STRENGTH"
        },
        "value": 25
      },
      {
        "display": {
          "color": {
            "a": 1.0,
            "b": 255,
            "g": 255,
            "r": 255
          },
          "display_string": "+37 Stamina"
        },
        "type": {
          "name": "Stamina",
          "type": "STAMINA"
        },
        "value": 37
      },
      {
        "display": {
          "color": {
            "a": 1.0,
            "b": 0,
            "g": 255,
            "r": 0
          },
          "display_string": "+23 Haste"
        },
        "is_equip_bonus": true,
        "type": {
          "name": "Haste",
          "type": "HASTE_RATING"
        },
        "value": 23
      },
      {
        "display": {
          "color": {
            "a": 1.0,
            "b": 0,
            "g": 255,
            "r": 0
          },
          "display_string": "+27 Versatility"
        },
        "is_equip_bonus": true,
        "type": {
          "name": "Versatility",
          "type": "VERSATILITY"
        },
        "value": 27
      }
    ]
  },
  "purchase_price": 1327019,
  "purchase_quantity": 1,
  "quality": {
    "name": "Uncommon",
    "type": "UNCOMMON"
  },
  "required_level": 60,
  "sell_price": 265403
}