{
  "_links": {
    "self": {
      "href": "https://eu.api.blizzard.com/data/wow/item/204728?namespace=static-11.1.0_59095-eu"
    }
  },
  "description": "It smells awful to you, but to the niffen it smells like friend.",
  "icon_path": "data\\icons\\inv_helm_misc_pignosemask_a_01.jpg",
  "id": 204728,
  "inventory_type": {
    "name": "Trinket",
    "type": "TRINKET"
  },
  "is_equippable": true,
  "is_stackable": false,
  "item_class": {
    "id": 4,
    "key": {
      "href": "https://eu.api.blizzard.com/data/wow/item-class/4?namespace=static-11.1.0_59095-eu"
    },
    "name": "Armor"
  },
  "item_subclass": {
    "id": 0,
    "key": {
      "href": "https://eu.api.blizzard.com/data/wow/item-class/4/item-subclass/0?namespace=static-11.1.0_59095-eu"
    },
    "name": "Miscellaneous"
  },
  "level": 250,
  "max_count": 0,
  "media": {
    "id": 204728,
    "key": {
      "href": "https://eu.api.blizzard.com/data/wow/media/item/204728?namespace=static-11.1.0_59095-eu"
    }
  },
  "name": "Friendship Censer",
  "preview_item": {
    "binding": {
      "name": "Binds when picked up",
      "type": "ON_ACQUIRE"
    },
    "bonus_list": [
      8902
    ],
    "context": 0,
    "description": "It smells awful to you, but to the niffen it smells like friend.",
    "inventory_type": {
      "name": "Trinket",
      "type": "TRINKET"
    },
    "is_subclass_hidden": true,
    "item": {
      "id": 204728,
      "key": {
        "href": "https://eu.api.blizzard.com/data/wow/item/204728?namespace=static-11.1.0_59095-eu"
      }
    },
    "item_class": {
      "id": 4,
      "key": {
        "href": "https://eu.api.blizzard.com/data/wow/item-class/4?namespace=static-11.1.0_59095-eu"
      },
      "name": "Armor"
    },
    "item_subclass": {
      "id": 0,
      "key": {
        "href": "https://eu.api.blizzard.com/data/wow/item-class/4/item-subclass/0?namespace=static-11.1.0_59095-eu"
      },
      "name": "Miscellaneous"
    },
    "level": {
      "display_string": "Item Level 250",
      "value": 250
    },
    "media": {
      "id": 204728,
      "key": {
        "href": "https://eu.api.blizzard.com/data/wow/media/item/204728?namespace=static-11.1.0_59095-eu"
      }
    },
    "name": "Friendship Censer",
    "quality": {
      "name": "Rare",
      "type": "RARE"
    },
    "requirements": {
      "level": {
        "display_string": "Requires Level 70",
        "value": 70
      }
    },
    "sell_price": {
      "display_strings": {
        "copper": "81",
        "gold": "6",
        "header": "Sell Price:",
        "silver": "89"
      },
      "value": 68981
    },
    "spells": [
      {
        "description": "Use: Call a friend to come help you! They may deal 10,866 Physical damage to your target and stun it for 2 sec, heal you for 17,753, or increase a random secondary stat by 361 for 20 sec.\r\n\r\nIf you're feeling hungry, they might even bring you some food! (1 Min 30 Sec Cooldown)",
        "spell": {
          "id": 406459,
          "key": {
            "href": "https://eu.api.blizzard.com/data/wow/spell/406459?namespace=static-11.1.0_59095-eu"
          },
          "name": "Censing Friendship"
        }
      }
    ],
    "stats": [
      {
        "display": {
          "color": {
            "a": 1.0,
            "b": 255,
            "g": 255,
            "r": 255
          },
          "display_string": "+64 Intellect"
        },
        "type": {
          "name": "Intellect",
          "type": "INTELLECT"
        },
        "value": 64
      },
      {
        "display": {
          "color": {
            "a": 1.0,
            "b": 128,
            "g": 128,
            "r": 128
          },
          "display_string": "+64 Agility"
        },
        "is_negated": true,
        "type": {
          "name": "Agility",
          "type": "AGILITY"
        },
        "value": 64
      },
      {
        "display": {
          "color": {
            "a": 1.0,
            "b": 128,
            "g": 128,
            "r": 128
          },
          "display_string": "+64 Strength"
        },
        "is_negated": true,
        "type": {
          "name": "Strength",
          "type": "STRENGTH"
        },
        "value": 64
      }
    ],
    "unique_equipped": "Unique-Equipped"
  },
  "purchase_price": 137962,
  "purchase_quantity": 1,
  "quality": {
    "name": "Rare",
    "type": "RARE"
  },
  "required_level": 70,
  "sell_price": 68981
}