{
  "_links": {
    "self": {
      "href": "https://eu.api.blizzard.com/data/wow/item/220310?namespace=static-11.1.0_59095-eu"
    }
  },
  "appearances": [
    {
      "id": 91116,
      "key": {
        "href": "https://eu.api.blizzard.com/data/wow/item-appearance/91116?namespace=static-11.1.0_59095-eu"
      }
    }
  ],
  "icon_path": "data\\icons\\inv_helm_cloth_undergroundquest_b_01.jpg",
  "id": 220310,
  "inventory_type": {
    "name": "Head",
    "type": "HEAD"
  },
  "is_equippable": true,
  "is_stackable": false,
  "item_class": {
    "id": 4,
    "key": {
      "href": "https://eu.api.blizzard.com/data/wow/item-class/4?namespace=static-11.1.0_59095-eu"
    },
    "name": "Armor"
  },
  "item_subclass": {
    "id": 1,
    "key": {
      "href": "https://eu.api.blizzard.com/data/wow/item-class/4/item-subclass/1?namespace=static-11.1.0_59095-eu"
    },
    "name": "Cloth"
  },
  "level": 400,
  "max_count": 0,
  "media": {
    "id": 220310,
    "key": {
      "href": "https://eu.api.blizzard.com/data/wow/media/item/220310?namespace=static-11.1.0_59095-eu"
    }
  },
  "name": "Moth-Ridden Hood",
  "preview_item": {
    "armor": {
      "display": {
        "color": {
          "a": 1.0,
          "b": 255,
          "g": 255,
          "r": 255
        },
        "display_string": "161 Armor"
      },
      "value": 161
    },
    "binding": {
      "name": "Binds when equipped",
      "type": "ON_EQUIP"
    },
    "bonus_list": [
      10350
    ],
    "context": 0,
    "durability": {
      "display_string": "Durability 70 / 70",
      "value": 70
    },
    "inventory_type": {
      "name": "Head",
      "type": "HEAD"
    },
    "item": {
      "id": 220310,
      "key": {
        "href": "https://eu.api.blizzard.com/data/wow/item/220310?namespace=static-11.1.0_59095-eu"
      }
    },
    "item_class": {
      "id": 4,
      "key": {
        "href": "https://eu.api.blizzard.com/data/wow/item-class/4?namespace=static-11.1.0_59095-eu"
      },
      "name": "Armor"
    },
    "item_subclass": {
      "id": 1,
      "key": {
        "href": "https://eu.api.blizzard.com/data/wow/item-class/4/item-subclass/1?namespace=static-11.1.0_59095-eu"
      },
      "name": "Cloth"
    },
    "level": {
      "display_string": "Item Level 362",
      "value": 362
    },
    "media": {
      "id": 220310,
      "key": {
        "href": "https://eu.api.blizzard.com/data/wow/media/item/220310?namespace=static-11.1.0_59095-eu"
      }
    },
    "name": "Moth-Ridden Hood",
    "quality": {
      "name": "Poor",
      "type": "POOR"
    },
    "requirements": {
      "level": {
        "display_string": "Requires Level 68",
        "value": 68
      }
    },
    "sell_price": {
      "display_strings": {
        "copper": "58",
        "gold": "10",
        "header": "Sell Price:",
        "silver": "46"
      },
      "value": 104658
    }
  },
  "purchase_price": 0,
  "purchase_quantity": 1,
  "quality": {
    "name": "Poor",
    "type": "POOR"
  },
  "required_level": 68,
  "sell_price": 0
}