{
  "_links": {
    "self": {
      "href": "https://eu.api.blizzard.com/data/wow/item/22540?namespace=static-11.1.0_59095-eu"
    }
  },
  "description": "Teaches you how to perform the Parry enchantment.",
  "icon_path": "data\\icons\\inv_misc_note_01.jpg",
  "id": 22540,
  "inventory_type": {
    "name": "Non-equippable",
    "type": "NON_EQUIP"
  },
  "is_equippable": false,
  "is_stackable": false,
  "item_class": {
    "id": 9,
    "key": {
      "href": "https://eu.api.blizzard.com/data/wow/item-class/9?namespace=static-11.1.0_59095-eu"
    },
    "name": "Recipe"
  },
  "item_subclass": {
    "id": 8,
    "key": {
      "href": "https://eu.api.blizzard.com/data/wow/item-class/9/item-subclass/8?namespace=static-11.1.0_59095-eu"
    },
    "name": "Enchanting"
  },
  "level": 1,
  "max_count": 0,
  "media": {
    "id": 22540,
    "key": {
      "href": "https://eu.api.blizzard.com/data/wow/media/item/22540?namespace=static-11.1.0_59095-eu"
    }
  },
  "name": "Formula: Enchant Shield - Parry",
  "preview_item": {
    "inventory_type": {
      "name": "Non-equippable",
      "type": "NON_EQUIP"
    },
    "is_subclass_hidden": true,
    "item": {
      "id": 22540,
      "key": {
        "href": "https://eu.api.blizzard.com/data/wow/item/22540?namespace=static-11.1.0_59095-eu"
      }
    },
    "item_class": {
      "id": 9,
      "key": {
        "href": "https://eu.api.blizzard.com/data/wow/item-class/9?namespace=static-11.1.0_59095-eu"
      },
      "name": "Recipe"
    },
    "item_subclass": {
      "id": 8,
      "key": {
        "href": "https://eu.api.blizzard.com/data/wow/item-class/9/item-subclass/8?namespace=static-11.1.0_59095-eu"
      },
      "name": "Enchanting"
    },
    "media": {
      "id": 22540,
      "key": {
        "href": "https://eu.api.blizzard.com/data/wow/media/item/22540?namespace=static-11.1.0_59095-eu"
      }
    },
    "name": "Formula: Enchant Shield - Parry",
    "quality": {
      "name": "Uncommon",
      "type": "UNCOMMON"
    },
    "requirements": {
      "skill": {
        "display_string": "Requires Outland Enchanting (40)",
        "level": 40,
        "profession": {
          "id": 2493,
          "key": {
            "href": "https://eu.api.blizzard.com/data/wow/profession/2493?namespace=static-11.1.0_59095-eu"
          },
          "name": "Outland Enchanting"
        }
      }
    },
    "sell_price": {
      "display_strings": {
        "copper": "0",
        "gold": "1",
        "header": "Sell Price:",
        "silver": "50"
      },
      "value": 15000
    },
    "spells": [
      {
        "description": "Use: Teaches you how to perform the Parry enchantment.",
        "spell": {
          "id": 27946,
          "key": {
            "href": "https://eu.api.blizzard.com/data/wow/spell/27946?namespace=static-11.1.0_59095-eu"
          },
          "name": "Parry"
        }
      }
    ]
  },
  "purchase_price": 60000,
  "purchase_quantity": 1,
  "quality": {
    "name": "Uncommon",
    "type": "UNCOMMON"
  },
  "required_level": 0,
  "sell_price": 15000
}