{
  "_links": {
    "self": {
      "href": "https://eu.api.blizzard.com/data/wow/item/38268?namespace=static-11.1.0_59095-eu"
    }
  },
  "appearances": [
    {
      "id": 6117,
      "key": {
        "href": "https://eu.api.blizzard.com/data/wow/item-appearance/6117?namespace=static-11.1.0_59095-eu"
      }
    }
  ],
  "description": "Give to a Friend",
  "icon_path": "data\\icons\\inv_gauntlets_09.jpg",
  "id": 38268,
  "inventory_type": {
    "name": "Held In Off-hand",
    "type": "HOLDABLE"
  },
  "is_equippable": true,
  "is_stackable": false,
  "item_class": {
    "id": 4,
    "key": {
      "href": "https://eu.api.blizzard.com/data/wow/item-class/4?namespace=static-11.1.0_59095-eu"
    },
    "name": "Armor"
  },
  "item_subclass": {
    "id": 0,
    "key": {
      "href": "https://eu.api.blizzard.com/data/wow/item-class/4/item-subclass/0?namespace=static-11.1.0_59095-eu"
    },
    "name": "Miscellaneous"
  },
  "level": 1,
  "max_count": 0,
  "media": {
    "id": 38268,
    "key": {
      "href": "https://eu.api.blizzard.com/data/wow/media/item/38268?namespace=static-11.1.0_59095-eu"
    }
  },
  "name": "Spare Hand",
  "preview_item": {
    "binding": {
      "name": "Binds when equipped",
      "type": "ON_EQUIP"
    },
    "description": "Give to a Friend",
    "inventory_type": {
      "name": "Held In Off-hand",
      "type": "HOLDABLE"
    },
    "is_subclass_hidden": true,
    "item": {
      "id": 38268,
      "key": {
        "href": "https://eu.api.blizzard.com/data/wow/item/38268?namespace=static-11.1.0_59095-eu"
      }
    },
    "item_class": {
      "id": 4,
      "key": {
        "href": "https://eu.api.blizzard.com/data/wow/item-class/4?namespace=static-11.1.0_59095-eu"
      },
      "name": "Armor"
    },
    "item_subclass": {
      "id": 0,
      "key": {
        "href": "https://eu.api.blizzard.com/data/wow/item-class/4/item-subclass/0?namespace=static-11.1.0_59095-eu"
      },
      "name": "Miscellaneous"
    },
    "level": {
      "display_string": "Item Level 1",
      "value": 1
    },
    "media": {
      "id": 38268,
      "key": {
        "href": "https://eu.api.blizzard.com/data/wow/media/item/38268?namespace=static-11.1.0_59095-eu"
      }
    },
    "name": "Spare Hand",
    "quality": {
      "name": "Poor",
      "type": "POOR"
    },
    "requirements": {
      "level": {
        "display_string": "Requires Level 27",
        "value": 27
      }
    },
    "sell_price": {
      "display_strings": {
        "copper": "4",
        "gold": "0",
        "header": "Sell Price:",
        "silver": "0"
      },
      "value": 4
    }
  },
  "purchase_price": 12,
  "purchase_quantity": 1,
  "quality": {
    "name": "Poor",
    "type": "POOR"
  },
  "required_level": 27,
  "sell_price": 2
}