{
  "_links": {
    "self": {
      "href": "https://eu.api.blizzard.com/data/wow/item/4191?namespace=static-11.1.0_59095-eu"
    }
  },
  "appearances": [
    {
      "id": 1537,
      "key": {
        "href": "https://eu.api.blizzard.com/data/wow/item-appearance/1537?namespace=static-11.1.0_59095-eu"
      }
    }
  ],
  "icon_path": "data\\icons\\inv_pants_02.jpg",
  "id": 4191,
  "inventory_type": {
    "name": "Legs",
    "type": "LEGS"
  },
  "is_equippable": true,
  "is_stackable": false,
  "item_class": {
    "id": 4,
    "key": {
      "href": "https://eu.api.blizzard.com/data/wow/item-class/4?namespace=static-11.1.0_59095-eu"
    },
    "name": "Armor"
  },
  "item_subclass": {
    "id": 2,
    "key": {
      "href": "https://eu.api.blizzard.com/data/wow/item-class/4/item-subclass/2?namespace=static-11.1.0_59095-eu"
    },
    "name": "Leather"
  },
  "level": 17,
  "max_count": 0,
  "media": {
    "id": 4191,
    "key": {
      "href": "https://eu.api.blizzard.com/data/wow/media/item/4191?namespace=static-11.1.0_59095-eu"
    }
  },
  "name": "Owlbeast Leggings",
  "preview_item": {
    "armor": {
      "display": {
        "color": {
          "a": 1.0,
          "b": 255,
          "g": 255,
          "r": 255
        },
        "display_string": "4 Armor"
      },
      "value": 4
    },
    "binding": {
      "name": "Binds when equipped",
      "type": "ON_EQUIP"
    },
    "durability": {
      "display_string": "Durability 65 / 65",
      "value": 65
    },
    "inventory_type": {
      "name": "Legs",
      "type": "LEGS"
    },
    "item": {
      "id": 4191,
      "key": {
        "href": "https://eu.api.blizzard.com/data/wow/item/4191?namespace=static-11.1.0_59095-eu"
      }
    },
    "item_class": {
      "id": 4,
      "key": {
        "href": "https://eu.api.blizzard.com/data/wow/item-class/4?namespace=static-11.1.0_59095-eu"
      },
      "name": "Armor"
    },
    "item_subclass": {
      "id": 2,
      "key": {
        "href": "https://eu.api.blizzard.com/data/wow/item-class/4/item-subclass/2?namespace=static-11.1.0_59095-eu"
      },
      "name": "Leather"
    },
    "level": {
      "display_string": "Item Level 17",
      "value": 17
    },
    "media": {
      "id": 4191,
      "key": {
        "href": "https://eu.api.blizzard.com/data/wow/media/item/4191?namespace=static-11.1.0_59095-eu"
      }
    },
    "name": "Owlbeast Leggings",
    "quality": {
      "name": "Common",
      "type": "COMMON"
    },
    "requirements": {
      "level": {
        "display_string": "Requires Level 10",
        "value": 10
      }
    },
    "sell_price": {
      "display_strings": {
        "copper": "31",
        "gold": "0",
        "header": "Sell Price:",
        "silver": "0"
      },
      "value": 31
    }
  },
  "purchase_price": 7207,
  "purchase_quantity": 1,
  "quality": {
    "name": "Common",
    "type": "COMMON"
  },
  "required_level": 10,
  "sell_price": 1441
}