{
  "_links": {
    "self": {
      "href": "https://eu.api.blizzard.com/data/wow/item/6367?namespace=static-11.1.0_59095-eu"
    }
  },
  "icon_path": "data\\icons\\inv_fishingpole_01.jpg",
  "id": 6367,
  "inventory_type": {
    "name": "Profession Tool",
    "type": "PROFESSION_TOOL"
  },
  "is_equippable": true,
  "is_stackable": false,
  "item_class": {
    "id": 19,
    "key": {
      "href": "https://eu.api.blizzard.com/data/wow/item-class/19?namespace=static-11.1.0_59095-eu"
    },
    "name": "Profession"
  },
  "item_subclass": {
    "id": 9,
    "key": {
      "href": "https://eu.api.blizzard.com/data/wow/item-class/19/item-subclass/9?namespace=static-11.1.0_59095-eu"
    },
    "name": "Fishing"
  },
  "level": 18,
  "max_count": 0,
  "media": {
    "id": 6367,
    "key": {
      "href": "https://eu.api.blizzard.com/data/wow/media/item/6367?namespace=static-11.1.0_59095-eu"
    }
  },
  "name": "Big Iron Fishing Pole",
  "preview_item": {
    "inventory_type": {
      "name": "Profession Tool",
      "type": "PROFESSION_TOOL"
    },
    "item": {
      "id": 6367,
      "key": {
        "href": "https://eu.api.blizzard.com/data/wow/item/6367?namespace=static-11.1.0_59095-eu"
      }
    },
    "item_class": {
      "id": 19,
      "key": {
        "href": "https://eu.api.blizzard.com/data/wow/item-class/19?namespace=static-11.1.0_59095-eu"
      },
      "name": "Profession"
    },
    "item_subclass": {
      "id": 9,
      "key": {
        "href": "https://eu.api.blizzard.com/data/wow/item-class/19/item-subclass/9?namespace=static-11.1.0_59095-eu"
      },
      "name": "Fishing"
    },
    "media": {
      "id": 6367,
      "key": {
        "href": "https://eu.api.blizzard.com/data/wow/media/item/6367?namespace=static-11.1.0_59095-eu"
      }
    },
    "name": "Big Iron Fishing Pole",
    "quality": {
      "name": "Common",
      "type": "COMMON"
    },
    "requirements": {
      "level": {
        "display_string": "Requires Level 11",
        "value": 11
      },
      "skill": {
        "display_string": "Requires Classic Fishing (100)",
        "level": 100,
        "profession": {
          "id": 2592,
          "key": {
            "href": "https://eu.api.blizzard.com/data/wow/profession/2592?namespace=static-11.1.0_59095-eu"
          },
          "name": "Classic Fishing"
        }
      }
    },
    "sell_price": {
      "display_strings": {
        "copper": "33",
        "gold": "0",
        "header": "Sell Price:",
        "silver": "21"
      },
      "value": 2133
    },
    "spells": [
      {
        "description": "Equip: +10 Fishing Skill.",
        "spell": {
          "id": 71435,
          "key": {
            "href": "https://eu.api.blizzard.com/data/wow/spell/71435?namespace=static-11.1.0_59095-eu"
          },
          "name": "+10 Fishing"
        }
      }
    ]
  },
  "purchase_price": 10665,
  "purchase_quantity": 1,
  "quality": {
    "name": "Common",
    "type": "COMMON"
  },
  "required_level": 11,
  "sell_price": 2133
}