{
  "_links": {
    "self": {
      "href": "https://eu.api.blizzard.com/data/wow/item/98856?namespace=static-11.1.0_59095-eu"
    }
  },
  "appearances": [
    {
      "id": 18384,
      "key": {
        "href": "https://eu.api.blizzard.com/data/wow/item-appearance/18384?namespace=static-11.1.0_59095-eu"
      }
    }
  ],
  "icon_path": "data\\icons\\inv_helmet_plate_pvppaladin_e_01.jpg",
  "id": 98856,
  "inventory_type": {
    "name": "Head",
    "type": "HEAD"
  },
  "is_equippable": true,
  "is_stackable": false,
  "item_class": {
    "id": 4,
    "key": {
      "href": "https://eu.api.blizzard.com/data/wow/item-class/4?namespace=static-11.1.0_59095-eu"
    },
    "name": "Armor"
  },
  "item_subclass": {
    "id": 4,
    "key": {
      "href": "https://eu.api.blizzard.com/data/wow/item-class/4/item-subclass/4?namespace=static-11.1.0_59095-eu"
    },
    "name": "Plate"
  },
  "level": 39,
  "max_count": 0,
  "media": {
    "id": 98856,
    "key": {
      "href": "https://eu.api.blizzard.com/data/wow/media/item/98856?namespace=static-11.1.0_59095-eu"
    }
  },
  "name": "Crafted Malevolent Gladiator's Ornamented Headcover",
  "preview_item": {
    "armor": {
      "display": {
        "color": {
          "a": 1.0,
          "b": 255,
          "g": 255,
          "r": 255
        },
        "display_string": "12 Armor"
      },
      "value": 12
    },
    "binding": {
      "name": "Binds when equipped",
      "type": "ON_EQUIP"
    },
    "durability": {
      "display_string": "Durability 85 / 85",
      "value": 85
    },
    "inventory_type": {
      "name": "Head",
      "type": "HEAD"
    },
    "item": {
      "id": 98856,
      "key": {
        "href": "https://eu.api.blizzard.com/data/wow/item/98856?namespace=static-11.1.0_59095-eu"
      }
    },
    "item_class": {
      "id": 4,
      "key": {
        "href": "https://eu.api.blizzard.com/data/wow/item-class/4?namespace=static-11.1.0_59095-eu"
      },
      "name": "Armor"
    },
    "item_subclass": {
      "id": 4,
      "key": {
        "href": "https://eu.api.blizzard.com/data/wow/item-class/4/item-subclass/4?namespace=static-11.1.0_59095-eu"
      },
      "name": "Plate"
    },
    "level": {
      "display_string": "Item Level 39",
      "value": 39
    },
    "media": {
      "id": 98856,
      "key": {
        "href": "https://eu.api.blizzard.com/data/wow/media/item/98856?namespace=static-11.1.0_59095-eu"
      }
    },
    "name": "Crafted Malevolent Gladiator's Ornamented Headcover",
    "quality": {
      "name": "Rare",
      "type": "RARE"
    },
    "requirements": {
      "level": {
        "display_string": "Requires Level 35",
        "value": 35
      },
      "playable_classes": {
        "display_string": "Classes: Paladin",
        "links": [
          {
            "id": 2,
            "key": {
              "href": "https://eu.api.blizzard.com/data/wow/playable-class/2?namespace=static-11.1.0_59095-eu"
            },
            "name": "Paladin"
          }
        ]
      }
    },
    "sell_price": {
      "display_strings": {
        "copper": "11",
        "gold": "0",
        "header": "Sell Price:",
        "silver": "3"
      },
      "value": 311
    },
    "set": {
      "display_string": "Gladiator's Redemption (0/5)",
      "effects": [
        {
          "display_string": "(2) Set: Increases the damage and healing of your Holy Shock spell by 10%.",
          "required_count": 2
        },
        {
          "display_string": "(4) Set: Casting Flash of Light grants 1 charge of Holy Power.",
          "required_count": 4
        }
      ],
      "item_set": {
        "id": 1110,
        "key": {
          "href": "https://eu.api.blizzard.com/data/wow/item-set/1110?namespace=static-11.1.0_59095-eu"
        },
        "name": "Gladiator's Redemption"
      },
      "items": [
        {
          "item": {
            "id": 88226,
            "key": {
              "href": "https://eu.api.blizzard.com/data/wow/item/88226?namespace=static-11.1.0_59095-eu"
            },
            "name": "Gladiator's Ornamented Chestguard"
          }
        },
        {
          "item": {
            "id": 88227,
            "key": {
              "href": "https://eu.api.blizzard.com/data/wow/item/88227?namespace=static-11.1.0_59095-eu"
            },
            "name": "Gladiator's Ornamented Gloves"
          }
        },
        {
          "item": {
            "id": 88228,
            "key": {
              "href": "https://eu.api.blizzard.com/data/wow/item/88228?namespace=static-11.1.0_59095-eu"
            },
            "name": "Gladiator's Ornamented Headcover"
          }
        },
        {
          "item": {
            "id": 88229,
            "key": {
              "href": "https://eu.api.blizzard.com/data/wow/item/88229?namespace=static-11.1.0_59095-eu"
            },
            "name": "Gladiator's Ornamented Legplates"
          }
        },
        {
          "item": {
            "id": 88230,
            "key": {
              "href": "https://eu.api.blizzard.com/data/wow/item/88230?namespace=static-11.1.0_59095-eu"
            },
            "name": "Gladiator's Ornamented Spaulders"
          }
        }
      ],
      "legacy": "Legacy Set: Bonus is inactive"
    },
    "socket_bonus": "Socket Bonus: +7 Versatility",
    "sockets": [
      {
        "socket_type": {
          "name": "Meta Socket",
          "type": "META"
        }
      },
      {
        "socket_type": {
          "name": "Prismatic Socket",
          "type": "PRISMATIC"
        }
      }
    ],
    "stats": [
      {
        "display": {
          "color": {
            "a": 1.0,
            "b": 255,
            "g": 255,
            "r": 255
          },
          "display_string": "+1 Intellect"
        },
        "type": {
          "name": "Intellect",
          "type": "INTELLECT"
        },
        "value": 1
      },
      {
        "display": {
          "color": {
            "a": 1.0,
            "b": 128,
            "g": 128,
            "r": 128
          },
          "display_string": "+1 Strength"
        },
        "is_negated": true,
        "type": {
          "name": "Strength",
          "type": "STRENGTH"
        },
        "value": 1
      },
      {
        "display": {
          "color": {
            "a": 1.0,
            "b": 255,
            "g": 255,
            "r": 255
          },
          "display_string": "+7 Stamina"
        },
        "type": {
          "name": "Stamina",
          "type": "STAMINA"
        },
        "value": 7
      },
      {
        "display": {
          "color": {
            "a": 1.0,
            "b": 0,
            "g": 255,
            "r": 0
          },
          "display_string": "+4 Critical Strike"
        },
        "is_equip_bonus": true,
        "type": {
          "name": "Critical Strike",
          "type": "CRIT_RATING"
        },
        "value": 4
      }
    ]
  },
  "purchase_price": 187396,
  "purchase_quantity": 1,
  "quality": {
    "name": "Rare",
    "type": "RARE"
  },
  "required_level": 35,
  "sell_price": 37479
}